genius/__init__.py
genius/api.py
genius/classes/__init__.py
genius/classes/album.py
genius/classes/artist.py
genius/classes/commons.py
genius/classes/media.py
genius/classes/social_media.py
genius/classes/song.py
genius/exceptions.py
genius/scraper.py
wrap_genius-1.8.0.dist-info/LICENSE
wrap_genius-1.8.0.dist-info/WHEEL
wrap_genius-1.8.0.dist-info/METADATA
wrap_genius-1.8.0.dist-info/RECORD
