Metadata-Version: 2.1
Name: wrap-genius
Version: 1.8.0
Summary: Python wrapper for api.genius.com
Home-page: https://github.com/fedecalendino/wrap-genius
License: MIT
Keywords: wrapper,genius.com
Author: Fede Calendino
Author-email: fede@calendino.com
Requires-Python: >=3.8,<4.0
Classifier: Intended Audience :: Developers
Classifier: License :: OSI Approved :: MIT License
Classifier: Programming Language :: Python :: 3
Classifier: Programming Language :: Python :: 3.10
Classifier: Programming Language :: Python :: 3.8
Classifier: Programming Language :: Python :: 3.9
Requires-Dist: Unidecode (>=1.3.4,<2.0.0)
Requires-Dist: beautifulsoup4 (>=4.11.1,<5.0.0)
Requires-Dist: requests (>=2.28.1,<3.0.0)
Project-URL: Documentation, https://github.com/fedecalendino/wrap-genius/blob/main/README.md
